<root>
  <integraltask id="1" level="1" integral="15,30,45,60,75,90,100,110,120,125" reward="0|1000000,1|50,2|17102,0|3000000,2|17202,1|200,2|17301,0|5000000,2|17303,1|1000" maxValue="130"/>
  <integraltask id="2" level="55" integral="15,30,45,60,75,90,105,115,125,130" reward="0|2000000,1|60,2|17203,0|4000000,2|17304,1|300,2|17305,0|6000000,2|174023,1|2000" maxValue="130"/>
  <integraltask id="3" level="70" integral="15,30,45,60,75,90,105,115,125,130" reward="0|3000000,1|70,2|17302,0|5000000,2|17305,1|400,2|174023,0|7000000,2|175015,1|3000" maxValue="130"/>
  <integraltask id="4" level="85" integral="15,30,45,60,75,90,105,115,120,127" reward="0|5000000,1|80,2|17305,0|7000000,2|174043,1|500,2|175015,0|8000000,2|175035|,1|4000" maxValue="130"/>
  <integraltask id="5" level="95" integral="15,30,45,60,75,90,105,115,120,127" reward="0|5000000,1|500,2|175015,0|7000000,2|175035,1|2000,2|73002,0|8000000,2|73002|,1|5500" maxValue="130"/>
  <integraltask id="6" level="110" integral="15,30,45,60,75,90,105,115,120,127" reward="0|5000000,1|1000,2|73002,0|7000000,2|175035,1|3000,2|73002,0|8000000,2|73002|,2|51041" maxValue="130"/>
  <integraltask id="7" level="180" integral="20,40,75,80,95,112,115,122,127,130" reward="0|7000000,1|1500,2|73002,0|9000000,2|175035,1|3500,2|73033,0|11000000,2|1200239|,2|51071" maxValue="130"/>
  <!--<integraltask id="7" level="120" integral="15,30,45,60,75,90,105,115,120,127" reward="2|50018,1|8,2|50019,2|50020,2|120046,1|23,2|50021,2|175035,2|73009,2|79003" maxValue="130"/>-->
</root>