<vipDesc>
<vip level = "0" desc=""/>
<vip level = "1" desc="{00ff00●1.开启装备传承系统}|{00ff00●2.可以使用宝石一键探索功能}|3.主船建筑队列可开启到3个|4.可开启伙伴训练位置到4个|5.伙伴训练可选择24小时训练|6.宠物可开启第5个携带位|7.行动力最多可购买15点|8.历练最大可加速次数10次|9.寻宝每日可购买刷新次数10次|10.竞技场最大可购买次数10次|11.每日金币出航最大次数40次|12.每日金币生产最大次数40次|13.会谈每日最大刷新次数30次|14.公会金币捐献可选择所有模式，可以通过更高级的捐献获取更多声望|15.公会积分每日自动贡献3积分"/>
<vip level = "2" desc="{00ff00●1.海贼团逆袭副本可以免费使用金币通关功能}|2.可延长科技CD为4小时|3.伙伴训练强度可选择噩梦训练|{00ff00●4.竞技场可直接跳过战斗}|5.行动力最多可购买20点|6.历练最大可加速次数15次|7.寻宝每日可购买刷新次数15次|8.竞技场最大可购买次数15次|9.每日金币出航最大次数60次|10.每日金币生产最大次数60次|11.会谈每日最大刷新次数60次|12.公会积分每日自动贡献5积分|13.包含VIP1所有功能"/>
<vip level = "3" desc="{00ff00●1.伙伴好感金币赠送每天可额外免费赠送三次}|{00ff00●2.可以使用世界Boss自动攻击功能}|{00ff00●3.每天可以免费使用1次金币聚魂}|4.主船建筑队列可开启到4个|5.宠物可开启第6个携带位|6.行动力最多可购买25点|7.历练可开通12小时模式|8.寻宝每日可购买刷新次数20次|9.竞技场最大可购买次数20次|10.每日金币出航最大次数80次|11.每日金币生产最大次数80次|12.会谈每日最大刷新次数80次|13.公会积分每日自动贡献7积分|14.包含VIP1-VIP2所有功能"/>
<vip level = "4" desc="{00ff00●1.每周可以免费潜能传承1次}|2.可开启伙伴训练位置到5个|3.行动力最多可购买30点|4.每日任务可使用金币直接完成|5.历练最大可加速次数20次|6.装备制作每日可开启工匠两次|7.装备制作可选择更高级制作模式|8.寻宝每日可购买刷新次数25次|9.潜能洗炼可选择大师洗炼|10.竞技场最大可购买次数25次|11.每日金币出航最大次数100次|12.每日金币生产最大次数100次|13.会谈每日最大刷新次数120次|14.公会积分每日自动贡献9积分|15.包含VIP1-VIP3所有功能"/>
<vip level = "5" desc="{00ff00●1.每天可以免费使用2次金币聚魂}|{00ff00●2.强化可永久开通100%模式}|{00ff00●3.宝石探索可使用金币直接开启第四场景，每次金币探索可获得一颗800经验的经验宝石}|4.主船建筑队列可开启到5个|5.伙伴训练可选择48小时训练|6.伙伴训练强度可选择地狱训练|7.宠物可开启第7个携带栏位|8.行动力最多可购买35点|9.宠物技能最多可锁定两格|10.可开启出航奇遇事件奖励显示|11.历练可开通24小时模式|12.寻宝每日可购买刷新次数30次|13.竞技场最大可购买次数30次|14.每日金币出航最大次数120次|15.每日金币生产最大次数120次|16.会谈每日最大刷新次数240次|17.公会积分每日自动贡献11积分|18.包含VIP1-VIP4所有功能"/>
<vip level = "6" desc="{00ff00●1.可以使用金币开启红船功能}|{00ff00●2.可以免费使用世界Boss离线自动攻打功能}|{00ff00●3.世界Boss可以使用立即复活功能}|4.装备制作每日可开启工匠3次|5.行动力最多可购买40点|6.寻宝每日可购买刷新次数40次|7.历练最大可加速次数25次|8.竞技场最大可购买次数35次|9.每日金币出航最大次数140次|10.每日金币生产最大次数140次|11.会谈每日最大刷新次数440次|12.公会积分每日自动贡献13积分|13.包含VIP1-VIP5所有功能"/>
<vip level = "7" desc="{00ff00●1.每天可以免费使用3次金币聚魂}|2.主船建筑队列可开启到6个|3.伙伴训练可选择72小时训练|4.可开启伙伴训练位置到6个|5.宠物可开启第8个携带栏位|6.行动力最多可购买45点|7.寻宝每日可购买刷新次数65次|8.历练最大可加速次数30次|9.竞技场最大可购买次数40次|10.每日金币出航最大次数160次|11.每日金币生产最大次数160次|12.会谈每日最大刷新次数700次|13.公会积分每日自动贡献15积分|13.包含VIP1-VIP6所有功能"/>
<vip level = "8" desc="1.行动力最多可购买50点|2.伙伴训练强度可选择魔鬼训练|3.可选择伙伴金币突飞|4.可选择宠物金币突飞|5.宠物技能最多可锁定3格|6.开启会谈同时刷新功能|7.装备制作可选择更高级制作模式|8.装备制作每日可开启工匠4次|{00ff00●9.潜能洗炼可选择宗师洗炼}|10.寻宝每日可购买刷新次数90次|11.历练最大可加速次数35次|12.竞技场最大可购买次数45次|13.每日金币出航最大次数180次|14.每日金币生产最大次数180次|15.会谈每日最大刷新次数1000次|16.公会积分每日自动贡献17积分|17.包含VIP1-VIP7所有功能"/>
<vip level = "9" desc="1.可开启伙伴训练位置到7个|{00ff00●2.会谈可开启永久免费刷新功能}|3.主船建筑队列可开启到7个|4.宠物可开启第9个携带栏位|5.行动力最多可购买55点|6.寻宝每日可购买刷新次数120次|7.历练最大可加速次数40次|8.竞技场最大可购买次数50次|9.每日金币出航最大次数200次|10.每日金币生产最大次数200次|11.会谈每日最大刷新次数无限|12.公会积分每日自动贡献19积分|13.包含VIP1-VIP8所有功能"/>
<vip level = "10" desc="1.主船建筑队列可开启到8个|2.可开启伙伴训练位置到8个|3.宠物可开启第10个携带栏位|4.行动力最多可购买60点|5.装备制作每日可开启工匠5次|6.寻宝每日可购买刷新次数150次|7.历练最大可加速次数45次|8.竞技场最大可购买次数55次|9.每日金币出航最大次数220次|10.每日金币生产最大次数220次|11.公会积分每日自动贡献21积分|12.包含VIP1-VIP9所有功能"/>
<vip level = "11" desc="{00ff00●1.每周可以免费潜能传承2次}|2.行动力最多可购买80点|3.装备制作每日可开启工匠6次|4.寻宝每日可购买刷新次数180次|5.历练最大可加速次数55次|6.竞技场最大可购买次数65次|7.每日金币出航最大次数300次|8.每日金币生产最大次数300次|9.公会积分每日自动贡献23积分|10.包含VIP1-VIP10所有功能"/>
<vip level = "12" desc="1.行动力最多可购买100点|2.装备制作每日可开启工匠7次|3.寻宝每日可购买刷新次数200次|4.历练最大可加速次数70次|5.竞技场最大可购买次数80次|6.每日金币出航最大次数400次|7.每日金币生产最大次数400次|8.公会积分每日自动贡献25积分|9.包含VIP1-VIP11所有功能"/>
</vipDesc>